crypto_connector/__init__.py
crypto_connector/binance.py
crypto_connector/htx.py
crypto_connector/base/__init__.py
crypto_connector/base/errors.py
crypto_connector/base/exchange.py
crypto_connector/base/schemas.py
crypto_connector-0.4.4.dist-info/METADATA
crypto_connector-0.4.4.dist-info/WHEEL
crypto_connector-0.4.4.dist-info/licenses/LICENSE
crypto_connector-0.4.4.dist-info/RECORD
