Metadata-Version: 2.4
Name: crypto-connector
Version: 0.4.4
Summary: A lightweight library that works as a connector to several crypto exchanges APIs.
Project-URL: Homepage, https://github.com/Izem0/crypto-connector
Project-URL: Issues, https://github.com/Izem0/crypto-connector/issues
Author-email: Izem Mangione <izem.mangione@gmail.com>
License-File: LICENSE
Classifier: License :: OSI Approved :: MIT License
Classifier: Operating System :: OS Independent
Classifier: Programming Language :: Python :: 3.10
Classifier: Programming Language :: Python :: 3.11
Classifier: Programming Language :: Python :: 3.12
Requires-Python: >=3.10
Requires-Dist: pydantic>=2.7.3
Requires-Dist: requests>=2.32.1
